src/__init__.py
src/jamie_hello.py
jamie-0.1.2.dist-info/LICENSE
jamie-0.1.2.dist-info/METADATA
jamie-0.1.2.dist-info/WHEEL
jamie-0.1.2.dist-info/top_level.txt
jamie-0.1.2.dist-info/RECORD
