Metadata-Version: 2.1
Name: jamie
Version: 0.1.2
Summary: A Python package developed for jamie's code
Home-page: https://github.com/PotatoXi/Jamie
Author: Jamie
Author-email: jmzhao29@gmail.com
License: BSD
Project-URL: Bug Tracker, https://github.com/PotatoXi/Jamie/issues
Platform: UNKNOWN
Classifier: Programming Language :: Python :: 3.9
Classifier: License :: OSI Approved :: BSD License
Classifier: Operating System :: OS Independent
Requires-Python: >=3.6
License-File: LICENSE
